CHANGES.rst
MANIFEST.in
README.rst
setup.py
pq/__init__.py
pq/create.sql
pq/tasks.py
pq/tests.py
pq/utils.py
pq.egg-info/PKG-INFO
pq.egg-info/SOURCES.txt
pq.egg-info/dependency_links.txt
pq.egg-info/not-zip-safe
pq.egg-info/top_level.txt