Metadata-Version: 1.1
Name: pq
Version: 1.7.0
Summary: PQ is a transactional queue for PostgreSQL.
Home-page: https://github.com/malthe/pq/
Author: Malthe Borch
Author-email: mborch@gmail.com
License: BSD
Platform: any
Classifier: Development Status :: 4 - Beta
Classifier: Intended Audience :: Developers
Classifier: Intended Audience :: Information Technology
Classifier: Intended Audience :: Science/Research
Classifier: Intended Audience :: System Administrators
Classifier: License :: OSI Approved :: BSD License
Classifier: Operating System :: POSIX
Classifier: Programming Language :: Python
Classifier: Topic :: Software Development :: Libraries :: Python Modules
Classifier: Topic :: Internet
Classifier: Topic :: System :: Distributed Computing
Classifier: Topic :: System :: Systems Administration
